SISO.v
module SISO(
    input clk, s_in, clear,
    output reg s_out
    );

    reg [3:0]internal_data;

    always @(posedge clk)begin
        if (clear)begin
            internal_data <= 4'b0;
            s_out <= 1'b0;
        end else begin
            internal_data <= {s_in, internal_data[3:1]};
            s_out <= internal_data[0];
        end
    end
endmodule

tb_SISO.v
`timescale 1ns/1ps

module tb_SISO();
    reg clk;
    reg clear;
    reg s_in;
    wire s_out;

    SISO uut (
        .s_in(s_in),
        .s_out(s_out),
        .clear(clear),
        .clk(clk)
    );

    initial clk = 1'b0;
    always #5 clk = ~clk;

    initial begin
        $dumpfile("SISOwaveform.vcd"); //Example input: 1011
        $dumpvars(0, tb_SISO);

        clear = 1; #10;
        $display("CLEAR = %b | OUTPUT = %b", clear, s_out);

        $display("CLEAR = %b | INPUT = %b | OUTPUT = %b", clear, s_in, s_out);
        clear = 0; #10;
        s_in = 1; #10;

        $display("CLEAR = %b | INPUT = %b | OUTPUT = %b", clear, s_in, s_out);
        s_in = 1; #10;

        $display("CLEAR = %b | INPUT = %b | OUTPUT = %b", clear, s_in, s_out);
        s_in = 0; #10;

        $display("CLEAR = %b | INPUT = %b | OUTPUT = %b", clear, s_in, s_out);
        s_in = 1; #10;

        #10; $display("CLEAR = %b | INPUT = %b | OUTPUT = %b", clear, s_in, s_out);

        #10; $display("CLEAR = %b | INPUT = %b | OUTPUT = %b", clear, s_in, s_out);

        #10; $display("CLEAR = %b | INPUT = %b | OUTPUT = %b", clear, s_in, s_out);

        #10; $display("CLEAR = %b | INPUT = %b | OUTPUT = %b", clear, s_in, s_out);

        clear = 1; #10;
        $display("CLEAR = %b | OUTPUT = %b", clear, s_out);
        $finish;
    end
endmodule

SISOwaveform.vcd
$date
	Thu Oct 02 11:25:42 2025
$end
$version
	Icarus Verilog
$end
$timescale
	1ps
$end
$scope module tb_SISO $end
$var wire 1 ! s_out $end
$var reg 1 " clear $end
$var reg 1 # clk $end
$var reg 1 $ s_in $end
$scope module uut $end
$var wire 1 " clear $end
$var wire 1 # clk $end
$var wire 1 $ s_in $end
$var reg 4 % internal_data [3:0] $end
$var reg 1 ! s_out $end
$upscope $end
$upscope $end
$enddefinitions $end
$comment Show the parameter values. $end
$dumpall
$end
#0
$dumpvars
bx %
x$
0#
1"
x!
$end
#5000
0!
b0 %
1#
#10000
0#
0"
#15000
bx000 %
1#
#20000
0#
1$
#25000
b1x00 %
1#
#30000
0#
#35000
b11x0 %
1#
#40000
0#
0$
#45000
b11x %
1#
#50000
0#
1$
#55000
x!
b1011 %
1#
#60000
0#
#65000
1!
b1101 %
1#
#70000
0#
#75000
b1110 %
1#
#80000
0#
#85000
0!
b1111 %
1#
#90000
0#
#95000
1!
1#
#100000
0#
1"
#105000
0!
b0 %
1#
